{
  "version": "1.0.0",
  "rss": "<LINK TO RSS FEED>",
  "discord": {
    "clientId": "<FILL IN OR REMOVE DISCORD OBJECT>",
    "smallImageText": "<FILL IN OR REMOVE DISCORD OBJECT>",
    "smallImageKey": "<FILL IN OR REMOVE DISCORD OBJECT>"
  },
  "servers": [
    {
      "id": "impulse_buying-1.20.1",
      "name": "충동구매",
      "description": "Minecraft 1.20.1 (Fabric v0.16.10)",
      "icon": "https://github.com/mchdistro/HM_TabooWord/raw/main/server-icon.png",
      "version": "1.0.0",
      "address": "mc.gotiger.dev:25563",
      "minecraftVersion": "1.20.1",
      "discord": {
        "shortId": "<FILL IN OR REMOVE DISCORD OBJECT>",
        "largeImageText": "<FILL IN OR REMOVE DISCORD OBJECT>",
        "largeImageKey": "<FILL IN OR REMOVE DISCORD OBJECT>"
      },
      "mainServer": true,
      "autoconnect": true,
      "modules": [
        {
          "id": "net.fabricmc:fabric-loader:0.16.10",
          "name": "Fabric (fabric-loader)",
          "type": "Fabric",
          "artifact": {
            "size": 1387408,
            "MD5": "239d59118dec4324672b3d9e9d75efef",
            "url": "https://github.com/mchdistro/HM_TabooWord/raw/main/repo/lib/net/fabricmc/fabric-loader/0.16.10/fabric-loader-0.16.10.jar"
          },
          "subModules": [
            {
              "id": "1.20.1-fabric-0.16.10",
              "name": "Fabric (version.json)",
              "type": "VersionManifest",
              "artifact": {
                "size": 2859,
                "MD5": "8e5d25d0c32f12aa0fb9f55d273cee04",
                "url": "https://github.com/mchdistro/HM_TabooWord/raw/main/repo/versions/1.20.1-fabric-0.16.10/1.20.1-fabric-0.16.10.json"
              }
            },
            {
              "id": "org.ow2.asm:asm:9.7.1",
              "name": "Fabric (asm)",
              "type": "Library",
              "artifact": {
                "size": 126093,
                "MD5": "e2cdd32d198ad31427d298eee9d39d8d",
                "url": "https://github.com/mchdistro/HM_TabooWord/raw/main/repo/lib/org/ow2/asm/asm/9.7.1/asm-9.7.1.jar"
              }
            },
            {
              "id": "org.ow2.asm:asm-analysis:9.7.1",
              "name": "Fabric (asm-analysis)",
              "type": "Library",
              "artifact": {
                "size": 35126,
                "MD5": "4cd9e7178dfb85371bba3077e40cd514",
                "url": "https://github.com/mchdistro/HM_TabooWord/raw/main/repo/lib/org/ow2/asm/asm-analysis/9.7.1/asm-analysis-9.7.1.jar"
              }
            },
            {
              "id": "org.ow2.asm:asm-commons:9.7.1",
              "name": "Fabric (asm-commons)",
              "type": "Library",
              "artifact": {
                "size": 73459,
                "MD5": "8344aea3c8b7d707e9d35a62710e77c9",
                "url": "https://github.com/mchdistro/HM_TabooWord/raw/main/repo/lib/org/ow2/asm/asm-commons/9.7.1/asm-commons-9.7.1.jar"
              }
            },
            {
              "id": "org.ow2.asm:asm-tree:9.7.1",
              "name": "Fabric (asm-tree)",
              "type": "Library",
              "artifact": {
                "size": 51939,
                "MD5": "e85029f613b6469989cc7cf53fe06b74",
                "url": "https://github.com/mchdistro/HM_TabooWord/raw/main/repo/lib/org/ow2/asm/asm-tree/9.7.1/asm-tree-9.7.1.jar"
              }
            },
            {
              "id": "org.ow2.asm:asm-util:9.7.1",
              "name": "Fabric (asm-util)",
              "type": "Library",
              "artifact": {
                "size": 94519,
                "MD5": "36d373a9cd6cad9b35db9f984c6b4bbb",
                "url": "https://github.com/mchdistro/HM_TabooWord/raw/main/repo/lib/org/ow2/asm/asm-util/9.7.1/asm-util-9.7.1.jar"
              }
            },
            {
              "id": "net.fabricmc:sponge-mixin:0.15.4+mixin.0.8.7",
              "name": "Fabric (sponge-mixin)",
              "type": "Library",
              "artifact": {
                "size": 1494834,
                "MD5": "991ca8be2c408fe19eb64014d8a18243",
                "url": "https://github.com/mchdistro/HM_TabooWord/raw/main/repo/lib/net/fabricmc/sponge-mixin/0.15.4+mixin.0.8.7/sponge-mixin-0.15.4+mixin.0.8.7.jar"
              }
            },
            {
              "id": "net.fabricmc:intermediary:1.20.1",
              "name": "Fabric (intermediary)",
              "type": "Library",
              "artifact": {
                "size": 573365,
                "MD5": "3f4768ac751cac3418266d1d7aa15f55",
                "url": "https://github.com/mchdistro/HM_TabooWord/raw/main/repo/lib/net/fabricmc/intermediary/1.20.1/intermediary-1.20.1.jar"
              }
            }
          ]
        },
        {
          "id": "me.axieum.mcmod.authme.impl:authme:7.0.2+1.20@jar",
          "name": "Auth Me",
          "type": "FabricMod",
          "artifact": {
            "size": 1250699,
            "url": "https://github.com/mchdistro/HM_TabooWord/raw/main/servers/impulse_buying-1.20.1/fabricmods/required/authme-7.0.2+1.20.jar",
            "MD5": "4154b45c0914932ce4c808b893f221f5"
          }
        },
        {
          "id": "me.shedaniel.autoconfig.example:cloth-config:11.1.136@jar",
          "name": "Cloth Config v11",
          "type": "FabricMod",
          "artifact": {
            "size": 1172214,
            "url": "https://github.com/mchdistro/HM_TabooWord/raw/main/servers/impulse_buying-1.20.1/fabricmods/required/cloth-config-11.1.136-fabric.jar",
            "MD5": "45d8bada7797af61d1f5543313b1f9f0"
          }
        },
        {
          "id": "generated.fabricmod:fabric-api:0.92.5+1.20.1@jar",
          "name": "Fabric API",
          "type": "FabricMod",
          "artifact": {
            "size": 2107841,
            "url": "https://github.com/mchdistro/HM_TabooWord/raw/main/servers/impulse_buying-1.20.1/fabricmods/required/fabric-api-0.92.5+1.20.1.jar",
            "MD5": "9d6b286586e9d6b40ee161dee1dd271f"
          }
        },
        {
          "id": "generated.fabricmod:ferritecore:6.0.1@jar",
          "name": "FerriteCore",
          "type": "FabricMod",
          "artifact": {
            "size": 125197,
            "url": "https://github.com/mchdistro/HM_TabooWord/raw/main/servers/impulse_buying-1.20.1/fabricmods/required/ferritecore-6.0.1-fabric.jar",
            "MD5": "a19272e427f75fea59127de6610ea26b"
          }
        },
        {
          "id": "generated.fabricmod:immediatelyfast:1.5.1+1.20.4@jar",
          "name": "ImmediatelyFast",
          "type": "FabricMod",
          "artifact": {
            "size": 242574,
            "url": "https://github.com/mchdistro/HM_TabooWord/raw/main/servers/impulse_buying-1.20.1/fabricmods/required/ImmediatelyFast-Fabric-1.5.1+1.20.4.jar",
            "MD5": "351dca2ff05cbc00c9a32eb45976cb73"
          }
        },
        {
          "id": "generated.fabricmod:iris:1.7.6+mc1.20.1@jar",
          "name": "Iris",
          "type": "FabricMod",
          "artifact": {
            "size": 2726899,
            "url": "https://github.com/mchdistro/HM_TabooWord/raw/main/servers/impulse_buying-1.20.1/fabricmods/required/iris-1.7.6+mc1.20.1.jar",
            "MD5": "45577adb5ab16505572c6ea4b1006e58"
          }
        },
        {
          "id": "journeymap:journeymap:5.10.3@jar",
          "name": "Journeymap",
          "type": "FabricMod",
          "artifact": {
            "size": 7209180,
            "url": "https://github.com/mchdistro/HM_TabooWord/raw/main/servers/impulse_buying-1.20.1/fabricmods/required/journeymap-1.20.1-5.10.3-fabric.jar",
            "MD5": "4689aa2b7ae8126112e32a2069dc1040"
          }
        },
        {
          "id": "com.hyfata.najoan:koreanpatch:1.6.13+mc1.20.1@jar",
          "name": "Korean Patch",
          "type": "FabricMod",
          "artifact": {
            "size": 448094,
            "url": "https://github.com/mchdistro/HM_TabooWord/raw/main/servers/impulse_buying-1.20.1/fabricmods/required/koreanpatch-fabric-1.6.13+mc1.20.1.jar",
            "MD5": "6e20891b8d2b8770569f819d4e765c4d"
          }
        },
        {
          "id": "me.jellysquid.mods:lithium:0.11.3@jar",
          "name": "Lithium",
          "type": "FabricMod",
          "artifact": {
            "size": 706600,
            "url": "https://github.com/mchdistro/HM_TabooWord/raw/main/servers/impulse_buying-1.20.1/fabricmods/required/lithium-fabric-mc1.20.1-0.11.3.jar",
            "MD5": "de6d394cedf7e33bfd4b03209156211a"
          }
        },
        {
          "id": "com.aizistral:nochatreports:1.20.1-v2.2.2@jar",
          "name": "No Chat Reports",
          "type": "FabricMod",
          "artifact": {
            "size": 619812,
            "url": "https://github.com/mchdistro/HM_TabooWord/raw/main/servers/impulse_buying-1.20.1/fabricmods/required/NoChatReports-FABRIC-1.20.1-v2.2.2.jar",
            "MD5": "62ebb770ad9e08008abf6df50a6a1aa7"
          }
        },
        {
          "id": "generated.fabricmod:sj_core:2.0.1.9@jar",
          "name": "SJ-Core",
          "type": "FabricMod",
          "artifact": {
            "size": 49079499,
            "url": "https://github.com/mchdistro/HM_TabooWord/raw/main/servers/impulse_buying-1.20.1/fabricmods/required/SJ-Core-2.0.1.9.jar",
            "MD5": "2475b40c44b9b15d8d266b6e9406a3d8"
          }
        },
        {
          "id": "net.sjhub.sjnick:sj_nick:0.0.9@jar",
          "name": "SJ-Nick",
          "type": "FabricMod",
          "artifact": {
            "size": 65857,
            "url": "https://github.com/mchdistro/HM_TabooWord/raw/main/servers/impulse_buying-1.20.1/fabricmods/required/SJ-Nick-0.0.9.jar",
            "MD5": "1d28eac260a093f94b20db43e28ab457"
          }
        },
        {
          "id": "me.jellysquid.mods:sodium:0.5.13+mc1.20.1@jar",
          "name": "Sodium",
          "type": "FabricMod",
          "artifact": {
            "size": 971552,
            "url": "https://github.com/mchdistro/HM_TabooWord/raw/main/servers/impulse_buying-1.20.1/fabricmods/required/sodium-fabric-0.5.13+mc1.20.1.jar",
            "MD5": "76e0349865f91f315aae087a6e88a84a"
          }
        },
        {
          "id": "de.maxhenkel:voicechat:1.20.1-2.5.29@jar",
          "name": "Simple Voice Chat",
          "type": "FabricMod",
          "artifact": {
            "size": 8100303,
            "url": "https://github.com/mchdistro/HM_TabooWord/raw/main/servers/impulse_buying-1.20.1/fabricmods/required/voicechat-fabric-1.20.1-2.5.29.jar",
            "MD5": "5c560a757ea07af13eb35ad3c6309955"
          }
        },
        {
          "id": "iris.properties",
          "name": "iris.properties",
          "type": "File",
          "artifact": {
            "size": 285,
            "url": "https://github.com/mchdistro/HM_TabooWord/raw/main/servers/impulse_buying-1.20.1/files/config/iris.properties",
            "path": "config/iris.properties"
          }
        },
        {
          "id": "xaerominimap.txt",
          "name": "xaerominimap.txt",
          "type": "File",
          "artifact": {
            "size": 3506,
            "url": "https://github.com/mchdistro/HM_TabooWord/raw/main/servers/impulse_buying-1.20.1/files/config/xaerominimap.txt",
            "path": "config/xaerominimap.txt"
          }
        },
        {
          "id": "options.txt",
          "name": "options.txt",
          "type": "File",
          "artifact": {
            "size": 2142,
            "url": "https://github.com/mchdistro/HM_TabooWord/raw/main/servers/impulse_buying-1.20.1/files/options.txt",
            "path": "options.txt"
          }
        },
        {
          "id": "servers.dat",
          "name": "servers.dat",
          "type": "File",
          "artifact": {
            "size": 114,
            "url": "https://github.com/mchdistro/HM_TabooWord/raw/main/servers/impulse_buying-1.20.1/files/servers.dat",
            "MD5": "09bb5964764a0b791427e55bc56fd40a",
            "path": "servers.dat"
          }
        },
        {
          "id": "ComplementaryUnbound_r5.2.2.zip",
          "name": "ComplementaryUnbound_r5.2.2.zip",
          "type": "File",
          "artifact": {
            "size": 441687,
            "url": "https://github.com/mchdistro/HM_TabooWord/raw/main/servers/impulse_buying-1.20.1/files/shaderpacks/ComplementaryUnbound_r5.2.2.zip",
            "MD5": "77b72dd3824ad2d6ddb1f952a786137c",
            "path": "shaderpacks/ComplementaryUnbound_r5.2.2.zip"
          }
        }
      ]
    }
  ]
}